Workbook

Sheet Управленческий вывод
A1: Повторяемый спрос: почему он сильнее разового промо-спроса
A3: Смысл примера | B3: Компания X выпускает бытовую химию. Традиционный сценарий продает первую покупку через скидку и промо. Сценарий Повторяемого спроса продает бытовой ритуал: регулярное пополнение, наборы по сценам уборки, CRM-возврат и снижение зависимости от скидки.
A6: Метрика | B6: Разовый промо-спрос | C6: Повторяемый спрос | D6: Разница | E6: Что видит собственник
A7: Первые покупатели | B7: ='P&L сравнение'!B6 | C7: ='P&L сравнение'!C6 | D7: =C7-B7 | E7: Повторяемый спрос может стартовать с меньшего охвата, но не обязан проигрывать экономику.
A8: Повторные покупатели | B8: ='P&L сравнение'!B10 | C8: ='P&L сравнение'!C10 | D8: =C8-B8 | E8: Главный источник денег - не первая акция, а возврат клиента.
A9: Повторная покупка | B9: ='P&L сравнение'!B9 | C9: ='P&L сравнение'!C9 | D9: =C9-B9 | E9: Повторяемость превращает бытовую химию из покупки по скидке в регулярный ритуал.
A10: Выручка | B10: ='P&L сравнение'!B15 | C10: ='P&L сравнение'!C15 | D10: =C10-B10 | E10: Выручка почти удваивается за счет повторов, а не за счет давления на скидку.
A11: Валовая прибыль | B11: ='P&L сравнение'!B20 | C11: ='P&L сравнение'!C20 | D11: =C11-B11 | E11: Валовая прибыль растет быстрее выручки, потому что меньше скидка.
A12: Коммерческие затраты | B12: ='P&L сравнение'!B26 | C12: ='P&L сравнение'!C26 | D12: =C12-B12 | E12: Затраты становятся инвестициями в возврат, а не платой за одноразовый промо-всплеск.
A13: Contribution profit, вклад в прибыль | B13: ='P&L сравнение'!B27 | C13: ='P&L сравнение'!C27 | D13: =C13-B13 | E13: Разница в прибыли показывает цену слабого спроса.
A14: Contribution margin, маржинальность вклада | B14: ='P&L сравнение'!B28 | C14: ='P&L сравнение'!C28 | D14: =C14-B14 | E14: Собственник видит не красивую коммуникацию, а экономику повторения.
A17: Короткий управленческий вывод | B17: Разовый промо-спрос покупает первую продажу и оставляет компанию с тонкой маржей. Повторяемый спрос строит причину вернуться: мотив, сцену уборки, ритуал пополнения и CRM-возврат. В примере компания получает не просто больше выручки, а в 10+ раз больший вклад в прибыль до фиксированных расходов.

Sheet Допущения
A1: Допущения модели: Компания X, бытовая химия
A3: Показатель | B3: Разовый промо-спрос | C3: Повторяемый спрос | D3: Ед. | E3: Комментарий
A4: Первые покупатели | B4: 100000 | C4: 85000 | D4: чел. | E4: Промо дает больше первого охвата; повторяемый спрос стартует осторожнее.
A5: Цена первой покупки | B5: 180 | C5: 220 | D5: руб. | E5: Промо-сценарий продает через скидку; повторяемый спрос допускает мягкий вход.
A6: Себестоимость единицы | B6: 95 | C6: 95 | D6: руб. | E6: Одинаковая продуктовая себестоимость.
A7: Логистика и выполнение | B7: 18 | C7: 18 | D7: руб./ед. | E7: Одинаковая операционная стоимость.
A8: Повторная покупка | B8: 0.18 | C8: 0.48 | D8: % | E8: Ритуал и CRM увеличивают долю клиентов, которые возвращаются.
A9: Повторные покупки на повторного клиента | B9: 1.5 | C9: 3 | D9: ед. | E9: Повторяемый спрос создает несколько циклов пополнения.
A10: Цена повторной покупки | B10: 230 | C10: 240 | D10: руб. | E10: Повторные покупки меньше зависят от скидки.
A11: Trade promo, торговое промо на первую покупку | B11: 35 | C11: 12 | D11: руб./первый покупатель | E11: Промо-сценарий субсидирует первую продажу.
A12: Media CAC, медийная стоимость привлечения | B12: 45 | C12: 35 | D12: руб./первый покупатель | E12: Повторяемый спрос меньше зависит от дорогого перезапуска охвата.
A13: CRM / ritual cost, стоимость поддержки ритуала | B13: 4 | C13: 18 | D13: руб./первый покупатель | E13: В повторяемом спросе появляются расходы на CRM, наборы, контент ритуала.
A14: Фиксированные маркетинговые расходы | B14: 1200000 | C14: 1500000 | D14: руб. | E14: Команда, аналитика, контентная система, бренд-материалы.
A15: Период модели | B15: 12 | C15: 12 | D15: мес. | E15: Управленческий пример за год.
A16: Название сценария 1 | B16: Разовый промо-спрос
A17: Название сценария 2 | C17: Повторяемый спрос
A18: Технология | C18: Повторяемый спрос, технология Повторяемого спроса

Sheet P&L сравнение
A1: Управленческая P&L: разовый промо-спрос vs Повторяемый спрос
A3: Строка P&L | B3: Разовый промо-спрос | C3: Повторяемый спрос | D3: Разница
A5: ДРАЙВЕРЫ
A6: Первые покупатели | B6: ='Допущения'!B4 | C6: ='Допущения'!C4 | D6: =C6-B6
A7: Цена первой покупки | B7: ='Допущения'!B5 | C7: ='Допущения'!C5 | D7: =C7-B7
A8: Выручка первой покупки | B8: =B6*B7 | C8: =C6*C7 | D8: =C8-B8
A9: Повторная покупка | B9: ='Допущения'!B8 | C9: ='Допущения'!C8 | D9: =C9-B9
A10: Повторные покупатели | B10: =B6*B9 | C10: =C6*C9 | D10: =C10-B10
A11: Повторные покупки на повторного клиента | B11: ='Допущения'!B9 | C11: ='Допущения'!C9 | D11: =C11-B11
A12: Повторные единицы | B12: =B10*B11 | C12: =C10*C11 | D12: =C12-B12
A13: Цена повторной покупки | B13: ='Допущения'!B10 | C13: ='Допущения'!C10 | D13: =C13-B13
A14: Выручка повторной покупки | B14: =B12*B13 | C14: =C12*C13 | D14: =C14-B14
A15: Итого выручка | B15: =B8+B14 | C15: =C8+C14 | D15: =C15-B15
A16: ПЕРЕМЕННЫЕ ЗАТРАТЫ | D16: 0
A17: Всего единиц | B17: =B6+B12 | C17: =C6+C12 | D17: =C17-B17
A18: Себестоимость | B18: =B17*'Допущения'!B6 | C18: =C17*'Допущения'!C6 | D18: =C18-B18
A19: Логистика | B19: =B17*'Допущения'!B7 | C19: =C17*'Допущения'!C7 | D19: =C19-B19
A20: Валовая прибыль | B20: =B15-B18-B19 | C20: =C15-C18-C19 | D20: =C20-B20
A21: Валовая маржа | B21: =B20/B15 | C21: =C20/C15 | D21: =C21-B21
A22: КОММЕРЧЕСКИЕ ЗАТРАТЫ | D22: 0
A23: Trade promo | B23: =B6*'Допущения'!B11 | C23: =C6*'Допущения'!C11 | D23: =C23-B23
A24: Media CAC | B24: =B6*'Допущения'!B12 | C24: =C6*'Допущения'!C12 | D24: =C24-B24
A25: CRM / ritual cost | B25: =B6*'Допущения'!B13 | C25: =C6*'Допущения'!C13 | D25: =C25-B25
A26: Итого коммерческие затраты | B26: =SUM(B23:B25) | C26: =SUM(C23:C25) | D26: =C26-B26
A27: Contribution profit | B27: =B20-B26 | C27: =C20-C26 | D27: =C27-B27
A28: Contribution margin | B28: =B27/B15 | C28: =C27/C15 | D28: =C28-B28
A29: Фиксированные маркетинговые расходы | B29: ='Допущения'!B14 | C29: ='Допущения'!C14 | D29: =C29-B29
A30: Operating profit до общих overhead | B30: =B27-B29 | C30: =C27-C29 | D30: =C30-B30

Sheet Воронка спроса
A1: Воронка спроса: где появляется экономика повторения
A3: Этап | B3: Разовый промо-спрос | C3: Повторяемый спрос | D3: Разница | E3: Управленческий смысл
A4: 1. Первый вход | B4: ='P&L сравнение'!B6 | C4: ='P&L сравнение'!C6 | D4: =C4-B4 | E4: Промо покупает больший первый вход, но это еще не бизнес-результат.
A5: 2. Цена входа | B5: ='P&L сравнение'!B7 | C5: ='P&L сравнение'!C7 | D5: =C5-B5 | E5: Скидка снижает ценность первой продажи.
A6: 3. Доля повтора | B6: ='P&L сравнение'!B9 | C6: ='P&L сравнение'!C9 | D6: =C6-B6 | E6: Главная точка технологии: вернуть клиента через мотив, сцену и ритуал.
A7: 4. Повторные покупатели | B7: ='P&L сравнение'!B10 | C7: ='P&L сравнение'!C10 | D7: =C7-B7 | E7: Рост повторных покупателей меняет всю P&L.
A8: 5. Повторные единицы | B8: ='P&L сравнение'!B12 | C8: ='P&L сравнение'!C12 | D8: =C8-B8 | E8: Появляется регулярный объем без повторной покупки внимания с нуля.
A9: 6. Выручка повтора | B9: ='P&L сравнение'!B14 | C9: ='P&L сравнение'!C14 | D9: =C9-B9 | E9: Повторная выручка создает устойчивость.
A10: 7. Вклад в прибыль | B10: ='P&L сравнение'!B27 | C10: ='P&L сравнение'!C27 | D10: =C10-B10 | E10: Вклад в прибыль показывает, сколько денег остается после прямых коммерческих затрат.
A11: 8. Операционная прибыль | B11: ='P&L сравнение'!B30 | C11: ='P&L сравнение'!C30 | D11: =C11-B11 | E11: Итог для собственника: меньше шума в продажах, больше управляемой прибыли.

Sheet Проверки
A1: Checks
A3: Check | B3: Formula | C3: Result | D3: Notes
A4: Revenue tie | B4: P&L revenue = first revenue + repeat revenue | C4: =IF(ABS('P&L сравнение'!B15-'P&L сравнение'!B8-'P&L сравнение'!B14)+ABS('P&L сравнение'!C15-'P&L сравнение'!C8-'P&L сравнение'!C14)<1,"PASS","FAIL") | D4: Both scenarios checked
A5: Gross profit tie | B5: Gross profit = revenue - COGS - logistics | C5: =IF(ABS('P&L сравнение'!B20-('P&L сравнение'!B15-'P&L сравнение'!B18-'P&L сравнение'!B19))+ABS('P&L сравнение'!C20-('P&L сравнение'!C15-'P&L сравнение'!C18-'P&L сравнение'!C19))<1,"PASS","FAIL") | D5: Both scenarios checked
A6: Commercial costs tie | B6: Commercial costs = promo + media + CRM/ritual | C6: =IF(ABS('P&L сравнение'!B26-SUM('P&L сравнение'!B23:B25))+ABS('P&L сравнение'!C26-SUM('P&L сравнение'!C23:C25))<1,"PASS","FAIL") | D6: Both scenarios checked
A7: Contribution tie | B7: Contribution = gross profit - commercial costs | C7: =IF(ABS('P&L сравнение'!B27-('P&L сравнение'!B20-'P&L сравнение'!B26))+ABS('P&L сравнение'!C27-('P&L сравнение'!C20-'P&L сравнение'!C26))<1,"PASS","FAIL") | D7: Both scenarios checked
A8: Operating profit tie | B8: Operating profit = contribution - fixed marketing | C8: =IF(ABS('P&L сравнение'!B30-('P&L сравнение'!B27-'P&L сравнение'!B29))+ABS('P&L сравнение'!C30-('P&L сравнение'!C27-'P&L сравнение'!C29))<1,"PASS","FAIL") | D8: Both scenarios checked
