Workbook

Sheet Демо-данные
A1: Демо-данные — Диагностика — Контур Маржи v2.0
A2: Статус | B2: Модельные данные. Не являются данными реального клиента.
A4: SKU | B4: Канал | C4: Выручка | D4: Себестоимость | E4: Комиссии | F4: Промо | G4: Логистика | H4: Ассортиментная прибыль | I4: Рентабельность продаж
A5: SKU-101 | B5: Маркетплейс | C5: 1250000 | D5: 740000 | E5: 185000 | F5: 92000 | G5: 61000 | H5: =C5-D5-E5-F5-G5 | I5: =IF(C5=0,0,H5/C5)
A6: SKU-102 | B6: Сайт | C6: 760000 | D6: 420000 | E6: 38000 | F6: 42000 | G6: 29000 | H6: =C6-D6-E6-F6-G6 | I6: =IF(C6=0,0,H6/C6)
A7: SKU-103 | B7: Розница | C7: 980000 | D7: 610000 | E7: 64000 | F7: 85000 | G7: 47000 | H7: =C7-D7-E7-F7-G7 | I7: =IF(C7=0,0,H7/C7)
A8: SKU-104 | B8: Опт | C8: 1320000 | D8: 910000 | E8: 22000 | F8: 30000 | G8: 76000 | H8: =C8-D8-E8-F8-G8 | I8: =IF(C8=0,0,H8/C8)
A9: SKU-105 | B9: Маркетплейс | C9: 690000 | D9: 430000 | E9: 122000 | F9: 65000 | G9: 54000 | H9: =C9-D9-E9-F9-G9 | I9: =IF(C9=0,0,H9/C9)
A12: Итоговая выручка | B12: =SUM(C5:C9)
A13: Итоговая ассортиментная прибыль | B13: =SUM(H5:H9)
A14: Средняя рентабельность продаж | B14: =IF(B12=0,0,B13/B12)
A16: Использование | B16: Этот лист нужен для обучения и демонстрации логики расчёта. Основные шаблоны остаются в остальных листах.

Sheet Пульт
A1: Контур Маржи — Диагностика
A3: Показатель | B3: Значение | D3: Зона | E3: Количество | F3: Доля
A4: Индекс зрелости 0-100 | B4: =SUM(B13:B17) | D4: красная | E4: =COUNTIF('SKU x канал'!L5:L104,D4) | F4: =IFERROR(E4/SUM($E$4:$E$6),0)
A5: Красных SKU x канал | B5: =COUNTIF('SKU x канал'!L5:L104,"красная") | D5: жёлтая | E5: =COUNTIF('SKU x канал'!L5:L104,D5) | F5: =IFERROR(E5/SUM($E$4:$E$6),0)
A6: Доля подтверждённых выводов | B6: =IFERROR(COUNTIF('Карта потерь'!D5:D50,"подтверждено")/COUNTA('Карта потерь'!D5:D50),0) | D6: зелёная | E6: =COUNTIF('SKU x канал'!L5:L104,D6) | F6: =IFERROR(E6/SUM($E$4:$E$6),0)
A7: Полнота данных | B7: =IFERROR(SUM('Карта данных'!G5:G16)/(COUNTA('Карта данных'!A5:A16)*2),0)
A8: Решений для сессии | B8: =COUNTA('Карта потерь'!H5:H50)
A9: Гипотез требует проверки | B9: =COUNTIF('Гипотезы'!F5:F50,"требует проверки") | D9: Правило чтения
A10: Готовность к сессии | B10: =IF(AND(B5>0,B8>=3),"готова","не готова") | D10: Красная зона без владельца считается отдельной красной зоной.
D11: Гипотеза не является фактом, пока не подтверждена данными.
A12: Блок зрелости | B12: Балл | D12: Решение без метрики проверки считается намерением.
A13: Данные | B13: =ROUND(IFERROR(SUM('Карта данных'!G5:G16)/(COUNTA('Карта данных'!A5:A16)*2),0)*20,0)
A14: Экономика | B14: =IF(COUNT('SKU x канал'!K5:K104)>0,20,0)
A15: Каналы | B15: =IF(COUNTA('SKU x канал'!C5:C104)>0,20,0)
A16: Решения | B16: =IF(COUNTA('Карта потерь'!H5:H50)>0,20,0)
A17: Ритм | B17: =IF(B8>=3,20,0)

Sheet Карта данных
A1: Карта данных
A4: Данные | B4: Есть / нет | C4: Источник | D4: Период | E4: Качество 0-2 | F4: Комментарий | G4: Балл
A5: Список SKU | G5: =IF(B5="есть",E5,IF(B5="частично",E5/2,0))
A6: Продажи по SKU | G6: =IF(B6="есть",E6,IF(B6="частично",E6/2,0))
A7: Продажи по каналам | G7: =IF(B7="есть",E7,IF(B7="частично",E7/2,0))
A8: Цены по каналам | G8: =IF(B8="есть",E8,IF(B8="частично",E8/2,0))
A9: Себестоимость | G9: =IF(B9="есть",E9,IF(B9="частично",E9/2,0))
A10: Комиссии | G10: =IF(B10="есть",E10,IF(B10="частично",E10/2,0))
A11: Промо и скидки | G11: =IF(B11="есть",E11,IF(B11="частично",E11/2,0))
A12: Запасы | G12: =IF(B12="есть",E12,IF(B12="частично",E12/2,0))
A13: Возвраты | G13: =IF(B13="есть",E13,IF(B13="частично",E13/2,0))
A14: Логистика | G14: =IF(B14="есть",E14,IF(B14="частично",E14/2,0))
A15: Штрафы | G15: =IF(B15="есть",E15,IF(B15="частично",E15/2,0))
A16: Ответственные | G16: =IF(B16="есть",E16,IF(B16="частично",E16/2,0))

Sheet SKU x канал
A1: SKU x канал
A4: SKU | B4: Категория | C4: Канал | D4: Выручка | E4: Себестоимость | F4: Комиссии | G4: Логистика | H4: Возвраты | I4: Промо | J4: Чистая прибыль | K4: Чистая маржа | L4: Зона | M4: Статус вывода | N4: Владелец проверки | O4: Решение для сессии
A5: SKU-001 | B5: Категория A | C5: Маркетплейс | D5: 100000 | E5: 60000 | F5: 12000 | G5: 7000 | H5: 5000 | I5: 8000 | J5: =IF(D5="","",D5-E5-F5-G5-H5-I5) | K5: =IF(D5="","",IFERROR(J5/D5,0)) | L5: =IF(K5="","",IF(K5<'Справочники'!$H$3,"красная",IF(K5<'Справочники'!$H$2,"жёлтая","зелёная")))
A6: SKU-002 | B6: Категория A | C6: Сеть | D6: 85000 | E6: 51000 | F6: 5000 | G6: 4000 | H6: 1500 | I6: 6000 | J6: =IF(D6="","",D6-E6-F6-G6-H6-I6) | K6: =IF(D6="","",IFERROR(J6/D6,0)) | L6: =IF(K6="","",IF(K6<'Справочники'!$H$3,"красная",IF(K6<'Справочники'!$H$2,"жёлтая","зелёная")))
A7: SKU-003 | B7: Категория B | C7: Прямой канал | D7: 120000 | E7: 65000 | F7: 3000 | G7: 6000 | H7: 2000 | I7: 10000 | J7: =IF(D7="","",D7-E7-F7-G7-H7-I7) | K7: =IF(D7="","",IFERROR(J7/D7,0)) | L7: =IF(K7="","",IF(K7<'Справочники'!$H$3,"красная",IF(K7<'Справочники'!$H$2,"жёлтая","зелёная")))
A8: SKU-004 | B8: Категория B | C8: Маркетплейс | D8: 60000 | E8: 39000 | F8: 9000 | G8: 5000 | H8: 4500 | I8: 6000 | J8: =IF(D8="","",D8-E8-F8-G8-H8-I8) | K8: =IF(D8="","",IFERROR(J8/D8,0)) | L8: =IF(K8="","",IF(K8<'Справочники'!$H$3,"красная",IF(K8<'Справочники'!$H$2,"жёлтая","зелёная")))
A9: SKU-005 | B9: Категория C | C9: Дистрибьютор | D9: 95000 | E9: 67000 | F9: 4000 | G9: 3000 | H9: 500 | I9: 2000 | J9: =IF(D9="","",D9-E9-F9-G9-H9-I9) | K9: =IF(D9="","",IFERROR(J9/D9,0)) | L9: =IF(K9="","",IF(K9<'Справочники'!$H$3,"красная",IF(K9<'Справочники'!$H$2,"жёлтая","зелёная")))
J10: =IF(D10="","",D10-E10-F10-G10-H10-I10) | K10: =IF(D10="","",IFERROR(J10/D10,0)) | L10: =IF(K10="","",IF(K10<'Справочники'!$H$3,"красная",IF(K10<'Справочники'!$H$2,"жёлтая","зелёная")))
J11: =IF(D11="","",D11-E11-F11-G11-H11-I11) | K11: =IF(D11="","",IFERROR(J11/D11,0)) | L11: =IF(K11="","",IF(K11<'Справочники'!$H$3,"красная",IF(K11<'Справочники'!$H$2,"жёлтая","зелёная")))
J12: =IF(D12="","",D12-E12-F12-G12-H12-I12) | K12: =IF(D12="","",IFERROR(J12/D12,0)) | L12: =IF(K12="","",IF(K12<'Справочники'!$H$3,"красная",IF(K12<'Справочники'!$H$2,"жёлтая","зелёная")))
J13: =IF(D13="","",D13-E13-F13-G13-H13-I13) | K13: =IF(D13="","",IFERROR(J13/D13,0)) | L13: =IF(K13="","",IF(K13<'Справочники'!$H$3,"красная",IF(K13<'Справочники'!$H$2,"жёлтая","зелёная")))
J14: =IF(D14="","",D14-E14-F14-G14-H14-I14) | K14: =IF(D14="","",IFERROR(J14/D14,0)) | L14: =IF(K14="","",IF(K14<'Справочники'!$H$3,"красная",IF(K14<'Справочники'!$H$2,"жёлтая","зелёная")))
J15: =IF(D15="","",D15-E15-F15-G15-H15-I15) | K15: =IF(D15="","",IFERROR(J15/D15,0)) | L15: =IF(K15="","",IF(K15<'Справочники'!$H$3,"красная",IF(K15<'Справочники'!$H$2,"жёлтая","зелёная")))
J16: =IF(D16="","",D16-E16-F16-G16-H16-I16) | K16: =IF(D16="","",IFERROR(J16/D16,0)) | L16: =IF(K16="","",IF(K16<'Справочники'!$H$3,"красная",IF(K16<'Справочники'!$H$2,"жёлтая","зелёная")))
J17: =IF(D17="","",D17-E17-F17-G17-H17-I17) | K17: =IF(D17="","",IFERROR(J17/D17,0)) | L17: =IF(K17="","",IF(K17<'Справочники'!$H$3,"красная",IF(K17<'Справочники'!$H$2,"жёлтая","зелёная")))
J18: =IF(D18="","",D18-E18-F18-G18-H18-I18) | K18: =IF(D18="","",IFERROR(J18/D18,0)) | L18: =IF(K18="","",IF(K18<'Справочники'!$H$3,"красная",IF(K18<'Справочники'!$H$2,"жёлтая","зелёная")))
J19: =IF(D19="","",D19-E19-F19-G19-H19-I19) | K19: =IF(D19="","",IFERROR(J19/D19,0)) | L19: =IF(K19="","",IF(K19<'Справочники'!$H$3,"красная",IF(K19<'Справочники'!$H$2,"жёлтая","зелёная")))
J20: =IF(D20="","",D20-E20-F20-G20-H20-I20) | K20: =IF(D20="","",IFERROR(J20/D20,0)) | L20: =IF(K20="","",IF(K20<'Справочники'!$H$3,"красная",IF(K20<'Справочники'!$H$2,"жёлтая","зелёная")))
J21: =IF(D21="","",D21-E21-F21-G21-H21-I21) | K21: =IF(D21="","",IFERROR(J21/D21,0)) | L21: =IF(K21="","",IF(K21<'Справочники'!$H$3,"красная",IF(K21<'Справочники'!$H$2,"жёлтая","зелёная")))
... J104: =IF(D104="","",D104-E104-F104-G104-H104-I104) | K104: =IF(D104="","",IFERROR(J104/D104,0)) | L104: =IF(K104="","",IF(K104<'Справочники'!$H$3,"красная",IF(K104<'Справочники'!$H$2,"жёлтая","зелёная")))

Sheet 12 метрик
A1: 12 метрик диагностики
A4: Метрика | B4: Направление | C4: Цель | D4: Факт | E4: Зона | F4: Статус вывода | G4: Комментарий
A5: Net Margin per SKU x канал / чистая маржа | B5: min | C5: 0.1 | E5: =IF(D5="","",IF(B5="min",IF(D5>=C5,"зелёная",IF(D5>=C5*0.8,"жёлтая","красная")),IF(B5="max",IF(D5<=C5,"зелёная",IF(D5<=C5*1.2,"жёлтая","красная")),IF(ABS(D5)<=C5,"зелёная",IF(ABS(D5)<=C5*1.4,"жёлтая","красная")))))
A6: ROMI / возврат маркетинга | B6: min | C6: 2.5 | E6: =IF(D6="","",IF(B6="min",IF(D6>=C6,"зелёная",IF(D6>=C6*0.8,"жёлтая","красная")),IF(B6="max",IF(D6<=C6,"зелёная",IF(D6<=C6*1.2,"жёлтая","красная")),IF(ABS(D6)<=C6,"зелёная",IF(ABS(D6)<=C6*1.4,"жёлтая","красная")))))
A7: CI / индекс каннибализации | B7: max | C7: 0.7 | E7: =IF(D7="","",IF(B7="min",IF(D7>=C7,"зелёная",IF(D7>=C7*0.8,"жёлтая","красная")),IF(B7="max",IF(D7<=C7,"зелёная",IF(D7<=C7*1.2,"жёлтая","красная")),IF(ABS(D7)<=C7,"зелёная",IF(ABS(D7)<=C7*1.4,"жёлтая","красная")))))
A8: Price Gap / ценовой разрыв | B8: range_abs | C8: 0.07 | E8: =IF(D8="","",IF(B8="min",IF(D8>=C8,"зелёная",IF(D8>=C8*0.8,"жёлтая","красная")),IF(B8="max",IF(D8<=C8,"зелёная",IF(D8<=C8*1.2,"жёлтая","красная")),IF(ABS(D8)<=C8,"зелёная",IF(ABS(D8)<=C8*1.4,"жёлтая","красная")))))
A9: CTR / доставка + возврат | B9: max | C9: 0.08 | E9: =IF(D9="","",IF(B9="min",IF(D9>=C9,"зелёная",IF(D9>=C9*0.8,"жёлтая","красная")),IF(B9="max",IF(D9<=C9,"зелёная",IF(D9<=C9*1.2,"жёлтая","красная")),IF(ABS(D9)<=C9,"зелёная",IF(ABS(D9)<=C9*1.4,"жёлтая","красная")))))
A10: DSI / дни запасов | B10: max | C10: 75 | E10: =IF(D10="","",IF(B10="min",IF(D10>=C10,"зелёная",IF(D10>=C10*0.8,"жёлтая","красная")),IF(B10="max",IF(D10<=C10,"зелёная",IF(D10<=C10*1.2,"жёлтая","красная")),IF(ABS(D10)<=C10,"зелёная",IF(ABS(D10)<=C10*1.4,"жёлтая","красная")))))
A11: OSA / наличие на полке | B11: min | C11: 0.95 | E11: =IF(D11="","",IF(B11="min",IF(D11>=C11,"зелёная",IF(D11>=C11*0.8,"жёлтая","красная")),IF(B11="max",IF(D11<=C11,"зелёная",IF(D11<=C11*1.2,"жёлтая","красная")),IF(ABS(D11)<=C11,"зелёная",IF(ABS(D11)<=C11*1.4,"жёлтая","красная")))))
A12: Buy-Box Win-Rate / победа в карточке | B12: min | C12: 0.7 | E12: =IF(D12="","",IF(B12="min",IF(D12>=C12,"зелёная",IF(D12>=C12*0.8,"жёлтая","красная")),IF(B12="max",IF(D12<=C12,"зелёная",IF(D12<=C12*1.2,"жёлтая","красная")),IF(ABS(D12)<=C12,"зелёная",IF(ABS(D12)<=C12*1.4,"жёлтая","красная")))))
A13: eNPS / индекс лояльности сотрудников | B13: min | C13: 30 | E13: =IF(D13="","",IF(B13="min",IF(D13>=C13,"зелёная",IF(D13>=C13*0.8,"жёлтая","красная")),IF(B13="max",IF(D13<=C13,"зелёная",IF(D13<=C13*1.2,"жёлтая","красная")),IF(ABS(D13)<=C13,"зелёная",IF(ABS(D13)<=C13*1.4,"жёлтая","красная")))))
A14: Penalty Rate / доля штрафов | B14: max | C14: 0.005 | E14: =IF(D14="","",IF(B14="min",IF(D14>=C14,"зелёная",IF(D14>=C14*0.8,"жёлтая","красная")),IF(B14="max",IF(D14<=C14,"зелёная",IF(D14<=C14*1.2,"жёлтая","красная")),IF(ABS(D14)<=C14,"зелёная",IF(ABS(D14)<=C14*1.4,"жёлтая","красная")))))
A15: NRL / чистые потери возвратов | B15: max | C15: 0.04 | E15: =IF(D15="","",IF(B15="min",IF(D15>=C15,"зелёная",IF(D15>=C15*0.8,"жёлтая","красная")),IF(B15="max",IF(D15<=C15,"зелёная",IF(D15<=C15*1.2,"жёлтая","красная")),IF(ABS(D15)<=C15,"зелёная",IF(ABS(D15)<=C15*1.4,"жёлтая","красная")))))
A16: TCI / транспортные затраты | B16: max | C16: 0.08 | E16: =IF(D16="","",IF(B16="min",IF(D16>=C16,"зелёная",IF(D16>=C16*0.8,"жёлтая","красная")),IF(B16="max",IF(D16<=C16,"зелёная",IF(D16<=C16*1.2,"жёлтая","красная")),IF(ABS(D16)<=C16,"зелёная",IF(ABS(D16)<=C16*1.4,"жёлтая","красная")))))

Sheet Карта потерь
A1: Карта потерь
A4: Зона потерь | B4: Что происходит | C4: Подтверждение данными | D4: Статус | E4: Потенциальное решение | F4: Приоритет | G4: Владелец проверки | H4: Решение для сессии
A5: Товарная матрица
A6: Каналы
A7: Цена
A8: Промо
A9: Комиссии
A10: Запасы
A11: Возвраты
A12: Упаковка / штрафы
A13: Ответственность

Sheet Гипотезы
A1: Гипотезы
A4: Гипотеза | B4: Почему возникла | C4: Какие данные нужны | D4: Как проверить | E4: Срок | F4: Статус

Sheet Справочники
A1: Статусы данных | B1: Качество данных | C1: Статусы вывода | D1: Зоны | E1: Приоритеты | G1: Порог | H1: Значение
A2: есть | B2: 2 | C2: подтверждено | D2: зелёная | E2: P0 | G2: Маржа зелёная от | H2: 0.1
A3: частично | B3: 1 | C3: требует проверки | D3: жёлтая | E3: P1 | G3: Маржа красная ниже | H3: 0.08
A4: нет | B4: 0 | C4: не подтверждено | D4: красная | E4: P2 | G4: Доля данных максимум | H4: 20
C5: модельный расчёт | E5: P3 | G5: Экономика максимум | H5: 20
G6: Каналы максимум | H6: 20
G7: Решения максимум | H7: 20
