Workbook

Sheet 00_Панель
A1: CLM Блок 3. Диагностическая панель
A3: Показатель | B3: Значение | C3: Норма | D3: Комментарий
A4: Клиент | B4: =IF('01_Ввод'!B4="","",'01_Ввод'!B4)
A5: CSS / индекс согласованности C-suite | B5: =IF('04_Расчет'!B6="","",'04_Расчет'!B6) | C5: 75+ | D5: =IF('04_Расчет'!B10="","",'04_Расчет'!B10)
A6: Статус | B6: =IF('04_Расчет'!B7="","",'04_Расчет'!B7) | C6: GO / HOLD / NO-GO
A7: Следующий блок | B7: =IF('05_Отчет'!B8="","",'05_Отчет'!B8)
A9: Рабочая книга облегчена: 7 листов вместо 23. FAQ и глоссарий вынесены в мастер-файлы. Основной ручной ввод сосредоточен на листах 01-03 и отчётном решении.
A11: Слой | B11: Заполненность | C11: Средний балл | D11: Источник
A12: Роли и мандаты | B12: ='04_Расчет'!B8 | C12: ='04_Расчет'!B4 | D12: 02_Роли_мандаты
A13: Решения и данные | B13: ='04_Расчет'!B9 | C13: ='04_Расчет'!B5 | D13: 03_Решения_данные
A14: Итог | B14: =IFERROR(AVERAGE(B12:B13),0) | C14: =IFERROR(AVERAGE(C12:C13),"") | D14: 04_Расчет
F16: Как пользоваться
F17: 1. Заполните лист 01_Ввод: клиент, дату, модель 7 / 15 / 23, сложность и главный симптом.
F18: 2. На листе 02_Роли_мандаты отметьте статус роли: выделена, совмещена или нет. Оценки 0-3 ставятся только там, где есть факты.
F19: 3. На листе 03_Решения_данные проверьте решения, данные, ритмы, доверие и AI / ИИ. Источник обязателен: интервью, документ, панель, протокол.
F20: 4. Лист 04_Расчет не заполняется вручную. Он считает CSS / индекс согласованности C-suite и заполненность.
F21: 5. На листе 05_Отчет выберите следующий блок CLM и добавьте короткий управленческий комментарий.
F22: Правило: пустое поле лучше, чем выдуманная оценка. Если нет источника, оценку не ставить.

Sheet 01_Ввод
A1: CLM Блок 3. Ввод диагностики
A3: Поле | B3: Значение
A4: Клиент
A5: Дата диагностики
A6: Выбранная модель
A7: Сложность бизнеса, 1-5
A8: Главный симптом
A9: Ответственный
A10: Комментарий
A12: Правило заполнения
A13: Заполняется только то, что влияет на итоговый вывод: модель, сложность, роли, мандаты, решения, данные, ритмы, доверие и AI / ИИ. Методология остается в DOCX, FAQ и глоссарии — в мастер-файлах.
A18: Помощь по заполнению
A19: Модель 7 / 15 / 23 | B19: Выбирается по сложности бизнеса. Не надо подгонять модель под количество людей в оргструктуре.
A20: Сложность 1-5 | B20: Оценивается экспертно: масштаб, цена ошибки, число решений, скорость изменений, число стыков между ролями.
A21: Главный симптом | B21: Один главный симптом лучше длинного описания. Детали уйдут в рабочие листы.

Sheet 02_Роли_мандаты
A1: Проверка ролей и мандатов
A4: Контур | B4: Роль | C4: Русское название | D4: Статус роли | E4: Владелец мандата | F4: Мандат ясен, 0-3 | G4: Право решения, 0-3 | H4: Риск потери, 0-3 | I4: Комментарий | J4: Балл
A5: Стратегическое ядро | B5: CEO | C5: Генеральный директор | J5: =IF(COUNTA(F5:H5)<3,"",ROUND((F5+G5+(3-H5))/3,1))
A6: Стратегическое ядро | B6: CVO Development | C6: Директор по развитию / стратегическому видению | J6: =IF(COUNTA(F6:H6)<3,"",ROUND((F6+G6+(3-H6))/3,1))
A7: Стратегическое ядро | B7: CFO | C7: Финансовый директор | J7: =IF(COUNTA(F7:H7)<3,"",ROUND((F7+G7+(3-H7))/3,1))
A8: Операционное ядро | B8: COO | C8: Операционный директор | J8: =IF(COUNTA(F8:H8)<3,"",ROUND((F8+G8+(3-H8))/3,1))
A9: Операционное ядро | B9: CAO Admin | C9: Административный директор | J9: =IF(COUNTA(F9:H9)<3,"",ROUND((F9+G9+(3-H9))/3,1))
A10: Операционное ядро | B10: CPO Procurement | C10: Директор по закупкам | J10: =IF(COUNTA(F10:H10)<3,"",ROUND((F10+G10+(3-H10))/3,1))
A11: Операционное ядро | B11: CRO Risk | C11: Директор по рискам | J11: =IF(COUNTA(F11:H11)<3,"",ROUND((F11+G11+(3-H11))/3,1))
A12: Операционное ядро | B12: CAO Accounting | C12: Главный бухгалтер / директор по учётному контуру | J12: =IF(COUNTA(F12:H12)<3,"",ROUND((F12+G12+(3-H12))/3,1))
A13: Коммерческое ядро | B13: CSO Sales | C13: Коммерческий директор / директор по продажам | J13: =IF(COUNTA(F13:H13)<3,"",ROUND((F13+G13+(3-H13))/3,1))
A14: Коммерческое ядро | B14: CMO | C14: Директор по маркетингу | J14: =IF(COUNTA(F14:H14)<3,"",ROUND((F14+G14+(3-H14))/3,1))
A15: Коммерческое ядро | B15: CPO Product | C15: Директор по продукту | J15: =IF(COUNTA(F15:H15)<3,"",ROUND((F15+G15+(3-H15))/3,1))
A16: Коммерческое ядро | B16: CRO Revenue | C16: Директор по доходам | J16: =IF(COUNTA(F16:H16)<3,"",ROUND((F16+G16+(3-H16))/3,1))
... A27: Инновационно-аналитический контур | B27: CVO Foresight | C27: Директор по форсайту / стратегическому прогнозированию | J27: =IF(COUNTA(F27:H27)<3,"",ROUND((F27+G27+(3-H27))/3,1))

Sheet 03_Решения_данные
A1: Проверка решений, данных, ритмов, доверия и AI / ИИ
A4: Слой | B4: Проверка | C4: Владелец | D4: Оценка, 0-3 | E4: Источник | F4: Комментарий | G4: Балл
A5: Решения | B5: Есть понятный владелец ключевых решений | G5: =IF(D5="","",D5)
A6: Решения | B6: Права решений не возвращаются постоянно к CEO / генеральному директору | G6: =IF(D6="","",D6)
A7: Решения | B7: Decision Loop / цикл решений доводит решения до исполнения | G7: =IF(D7="","",D7)
A8: Данные | B8: Есть единая версия фактов по ключевым показателям | G8: =IF(D8="","",D8)
A9: Данные | B9: У данных есть владелец качества | G9: =IF(D9="","",D9)
A10: Данные | B10: CFO, COO и CSO Sales не спорят о базовых цифрах | G10: =IF(D10="","",D10)
A11: Ритмы | B11: Ритм C-level фиксирует обязательства, а не только обсуждения | G11: =IF(D11="","",D11)
A12: Ритмы | B12: Есть регулярный review / разбор невыполненных решений | G12: =IF(D12="","",D12)
A13: Доверие | B13: Мандаты можно передавать без ручного контроля CEO | G13: =IF(D13="","",D13)
A14: Доверие | B14: Конфликты между ролями разбираются через правила, а не через силу статуса | G14: =IF(D14="","",D14)
A15: AI / ИИ | B15: Есть владелец AI / ИИ-мандата | G15: =IF(D15="","",D15)
A16: AI / ИИ | B16: AI / ИИ связан с данными, экономикой и ответственностью | G16: =IF(D16="","",D16)

Sheet 04_Расчет
A1: Расчёт диагностики
A3: Показатель | B3: Формула / значение | C3: Интерпретация | D3: Источник | F3: Как читать расчет
A4: Средний балл ролей и мандатов | B4: =IFERROR(AVERAGE('02_Роли_мандаты'!J5:J27),"") | C4: 0-3 | D4: 02_Роли_мандаты | F4: CSS / индекс согласованности C-suite — это рабочий сигнал, а не академическая точность.
A5: Средний балл решений и данных | B5: =IFERROR(AVERAGE('03_Решения_данные'!G5:G16),"") | C5: 0-3 | D5: 03_Решения_данные | F5: GO / запускать: разрывы локальны. HOLD / пауза: есть значимые разрывы. NO-GO / остановить: ядро не работает как система.
A6: CSS / индекс согласованности C-suite | B6: =IF(COUNTA(B4:B5)=0,"",IFERROR(ROUND(AVERAGE(B4:B5)/3*100,0),"")) | C6: 0-100 | D6: Среднее двух блоков
A7: Статус | B7: =IF(B6="","",IF(B6>=75,"GO / запускать",IF(B6>=50,"HOLD / пауза","NO-GO / остановить"))) | C7: GO / HOLD / NO-GO | D7: Порог CSS
A8: Заполненность ролей | B8: =IFERROR(COUNT('02_Роли_мандаты'!J5:J27)/23,0) | C8: Доля заполненных проверок | D8: 02_Роли_мандаты
A9: Заполненность решений | B9: =IFERROR(COUNT('03_Решения_данные'!G5:G16)/12,0) | C9: Доля заполненных проверок | D9: 03_Решения_данные
A10: Главный риск | B10: =IF(B6="","",IF(B6<50,"C-level-ядро не работает как система",IF(B6<75,"Есть значимые разрывы ролей, мандатов или данных","Разрывы локальны"))) | C10: Автовывод | D10: Статус + комментарии
A11: Следующий блок | C11: Выбирается в отчёте | D11: 05_Отчет
A12: Дата обновления | B12: ='01_Ввод'!B5 | C12: Ручной ввод | D12: 01_Ввод

Sheet 05_Отчет
A1: Отчёт Блока 3
A3: Поле | B3: Вывод | F3: Шаблон короткого вывода
A4: Клиент | B4: =IF('01_Ввод'!B4="","",'01_Ввод'!B4) | F4: Формула: главный разрыв → управленческий риск → следующий блок CLM → первое действие 30 дней.
A5: CSS / индекс согласованности C-suite | B5: =IF('04_Расчет'!B6="","",'04_Расчет'!B6) | F5: Пример: решения возвращаются к CEO → мандаты не держатся → Блок 5 → закрепить владельцев решений и ритм review / разбора.
A6: Статус | B6: =IF('04_Расчет'!B7="","",'04_Расчет'!B7)
A7: Главный риск | B7: =IF('04_Расчет'!B10="","",'04_Расчет'!B10)
A8: Рекомендуемый следующий блок
A9: Комментарий консультанта
A11: Выводы для заинтересованных сторон
A12: Сторона | B12: Что показать | C12: Что не включать | D12: Решение
A13: CEO / генеральный директор | B13: Где решения возвращаются к CEO и какие мандаты нужно закрепить | C13: Психологические оценки директоров
A14: C-level-команда / первый управленческий круг | B14: Какие роли, данные, ритмы и связки мешают общему результату | C14: Обвинительный список претензий
A15: Владелец компании | B15: Какие системные разрывы угрожают стоимости, скорости и управляемости | C15: Детали всех рабочих строк
A16: Board / совет директоров | B16: Какой управленческий риск выявлен и какой блок CLM нужен дальше | C16: Операционные мелочи без решения
A18: Карта выбора следующего блока
A19: Сигнал | B19: Следующий блок | C19: Почему
A20: Роль есть формально, но не держит мандат | B20: Блок 4 | C20: Оценить руководителя относительно роли и мандата
A21: Решения застревают между ролями | B21: Блок 5 | C21: Собрать Decision OS / операционную систему решений
A22: Функции спорят о KPI / ключевых показателях | B22: Блок 6 | C22: Сшить роли, показатели, доверие и общий ритм
A23: Команда не держит нагрузку | B23: Блок 7 | C23: Проверить устойчивость C-level-ядра
A24: CEO держит всё вручную | B24: Блок 8 | C24: Перевести лидерство от контроля к мандатам
A25: AI / ИИ влияет на работу без владельца | B25: Блок 9 | C25: Встроить AI / ИИ в мандаты, данные и ответственность
A26: Нет постоянной панели состояния | B26: Блок 10 | C26: Собрать панель 7 приборов CLM

Sheet 90_Справочник
A1: Контур | B1: Роль | C1: Русское название | D1: Мандаты | F1: Статус роли | G1: Оценка | H1: Модель | I1: Статус
A2: Стратегическое ядро | B2: CEO | C2: Генеральный директор | D2: Стратегический курс; целостность C-level-ядра; финальный выбор | F2: Выделена | G2: 0 | H2: 7 | I2: GO / запускать
A3: Стратегическое ядро | B3: CVO Development | C3: Директор по развитию / стратегическому видению | D3: Развитие бизнеса; стратегические инициативы; новые направления | F3: Совмещена | G3: 1 | H3: 15 | I3: HOLD / пауза
A4: Стратегическое ядро | B4: CFO | C4: Финансовый директор | D4: P&L / прибыль и убытки; cash flow / денежный поток; финансовая проверка решений | F4: Нет | G4: 2 | H4: 23 | I4: NO-GO / остановить
A5: Операционное ядро | B5: COO | C5: Операционный директор | D5: Исполнение; процессы; производительность; устранение узких мест | G5: 3
A6: Операционное ядро | B6: CAO Admin | C6: Административный директор | D6: Административный порядок; внутренние сервисы; регламенты
A7: Операционное ядро | B7: CPO Procurement | C7: Директор по закупкам | D7: Закупки; поставщики; TCO / совокупная стоимость владения
A8: Операционное ядро | B8: CRO Risk | C8: Директор по рискам | D8: Риск-карта; риск-аппетит; сценарные риски
A9: Операционное ядро | B9: CAO Accounting | C9: Главный бухгалтер / директор по учётному контуру | D9: Учёт; налоги; достоверность финансовых данных
A10: Коммерческое ядро | B10: CSO Sales | C10: Коммерческий директор / директор по продажам | D10: Продажи; pipeline / воронка продаж; коммерческое исполнение
A11: Коммерческое ядро | B11: CMO | C11: Директор по маркетингу | D11: Спрос; бренд; маркетинговая эффективность
A12: Коммерческое ядро | B12: CPO Product | C12: Директор по продукту | D12: Продуктовая ценность; roadmap / дорожная карта; экономика продукта
A13: Коммерческое ядро | B13: CRO Revenue | C13: Директор по доходам | D13: Монетизация; жизненный цикл выручки; удержание дохода
A14: Технологическое ядро | B14: CTO | C14: Технический директор | D14: Технологическая архитектура; разработка; инженерная устойчивость
A15: Технологическое ядро | B15: CIO | C15: Директор по информационным технологиям | D15: ИТ-инфраструктура; системы; доступы; данные
A16: Технологическое ядро | B16: CAIO | C16: Директор по искусственному интеллекту | D16: AI / ИИ-стратегия; портфель кейсов; управление рисками
A17: Технологическое ядро | B17: CDO | C17: Цифровой директор | D17: Цифровая трансформация; цифровые каналы; digital / цифровая архитектура
... A24: Инновационно-аналитический контур | B24: CVO Foresight | C24: Директор по форсайту / стратегическому прогнозированию | D24: Слабые сигналы; сценарии; будущие развилки
