Workbook

Sheet 00_Панель
A1: CLM Блок 6. Панель синхронизации
A3: Показатель | B3: Значение | C3: Норма | D3: Комментарий
A4: Клиент | B4: ='01_Ввод'!B4
A5: Заполненность интерфейсов | B5: ='04_Расчет'!B4 | C5: 80%+
A6: Средний балл интерфейсов | B6: ='04_Расчет'!B5 | C6: 2.3+
A7: Критичные зоны | B7: ='04_Расчет'!B7+'04_Расчет'!B8 | C7: 0
A8: Synchronization Score | B8: ='04_Расчет'!B9 | C8: 75+
A9: Статус | B9: ='04_Расчет'!B10 | C9: GO / HOLD / NO-GO
A11: Контроль заполнения | F11: Что проверяет Блок 6
A12: Слой | B12: Заполненность / число | C12: Норма | D12: Комментарий | F12: Блок 6 проверяет не личные отношения, а рабочие интерфейсы ролей: KPI / показатели, данные, решения, обязательства и доверие.
A13: Интерфейсы ролей | B13: ='04_Расчет'!B4 | C13: 80%+ | F13: Если связка ролей ломается под нагрузкой, это вход в Блок 7. Если держится только на CEO — вход в Блок 8.
A14: Ритм и доверие | B14: ='04_Расчет'!B6 | C14: 2.3+
A15: Критичные зоны | B15: ='04_Расчет'!B7+'04_Расчет'!B8 | C15: 0
A17: Как пользоваться
A18: 1. Заполните 01_Ввод: разрывы из Блоков 3–5 и главную конфликтующую связку.
A19: 2. На 02_Интерфейсы оцените связки ролей, KPI, данные, решения и владельца стыка.
A20: 3. На 03_Ритм_доверие проверьте обязательства, доверие и регулярный review / разбор.
A21: 4. 04_Расчет не заполняется вручную.
A22: 5. На 05_Отчет выберите следующий блок: чаще всего Блок 7, если связка ломается под нагрузкой.

Sheet 01_Ввод
A1: CLM Блок 6. Ввод синхронизации C-level-ядра
A3: Поле | B3: Значение
A4: Клиент
A5: Дата запуска
A6: Разрыв из Блока 3
A7: Риск роли из Блока 4
A8: Сбой Decision OS из Блока 5
A9: Главная конфликтующая связка
A10: Владелец синхронизации
A11: Ритм синхронизации
A12: Комментарий
A14: Правило заполнения
A15: 1 | B15: Фиксируйте не личный конфликт, а управленческий разрыв между ролями.
A16: 2 | B16: Главный объект Блока 6 — интерфейс ролей, KPI / показатели, данные, обязательства и доверие.
A17: 3 | B17: Если конфликт закрывается только CEO, это риск для Блока 8.
A18: 4 | B18: Если связка ломается под нагрузкой, это вход в Блок 7.

Sheet 02_Интерфейсы
A1: Карта интерфейсов ролей
A3: Связка ролей | B3: Зона синхронизации | C3: Главный конфликт KPI | D3: Общие данные | E3: Общее решение | F3: Владелец стыка | G3: Оценка, 0-3 | H3: Риск, 0-3 | I3: Комментарий / источник | J3: Балл | K3: Статус
A4: CEO / CFO | B4: Стратегия, деньги, инвестиции, ограничения | J4: =IF(COUNTA(G4:H4)<2,"",ROUND((G4+(3-H4))/2,1)) | K4: =IF(J4="","Не заполнено",IF(J4<1.5,"Критично",IF(J4<2.3,"Разрыв","ОК")))
A5: CEO / COO | B5: Приоритеты, исполнение, скорость изменений | J5: =IF(COUNTA(G5:H5)<2,"",ROUND((G5+(3-H5))/2,1)) | K5: =IF(J5="","Не заполнено",IF(J5<1.5,"Критично",IF(J5<2.3,"Разрыв","ОК")))
A6: CFO / COO | B6: Бюджет, ресурсы, производительность, экономия | J6: =IF(COUNTA(G6:H6)<2,"",ROUND((G6+(3-H6))/2,1)) | K6: =IF(J6="","Не заполнено",IF(J6<1.5,"Критично",IF(J6<2.3,"Разрыв","ОК")))
A7: CSO Sales / CMO | B7: Спрос, лиды, воронка продаж, качество клиентов | J7: =IF(COUNTA(G7:H7)<2,"",ROUND((G7+(3-H7))/2,1)) | K7: =IF(J7="","Не заполнено",IF(J7<1.5,"Критично",IF(J7<2.3,"Разрыв","ОК")))
A8: CSO Sales / CPO Product | B8: Обещания рынку, продуктовая ценность, roadmap / дорожная карта | J8: =IF(COUNTA(G8:H8)<2,"",ROUND((G8+(3-H8))/2,1)) | K8: =IF(J8="","Не заполнено",IF(J8<1.5,"Критично",IF(J8<2.3,"Разрыв","ОК")))
A9: CPO Product / CTO | B9: Продуктовые решения, сроки разработки, технический долг | J9: =IF(COUNTA(G9:H9)<2,"",ROUND((G9+(3-H9))/2,1)) | K9: =IF(J9="","Не заполнено",IF(J9<1.5,"Критично",IF(J9<2.3,"Разрыв","ОК")))
A10: COO / CHRO | B10: Производительность, оргизменения, люди, нагрузка | J10: =IF(COUNTA(G10:H10)<2,"",ROUND((G10+(3-H10))/2,1)) | K10: =IF(J10="","Не заполнено",IF(J10<1.5,"Критично",IF(J10<2.3,"Разрыв","ОК")))
A11: CIO / CAO Analytics | B11: Системы, данные, единая версия фактов | J11: =IF(COUNTA(G11:H11)<2,"",ROUND((G11+(3-H11))/2,1)) | K11: =IF(J11="","Не заполнено",IF(J11<1.5,"Критично",IF(J11<2.3,"Разрыв","ОК")))
A12: CRO Risk / CCO | B12: Риск, допустимость, комплаенс, контроль | J12: =IF(COUNTA(G12:H12)<2,"",ROUND((G12+(3-H12))/2,1)) | K12: =IF(J12="","Не заполнено",IF(J12<1.5,"Критично",IF(J12<2.3,"Разрыв","ОК")))
A13: CAIO / CIO | B13: AI / ИИ-сценарии, данные, безопасность, интеграция | J13: =IF(COUNTA(G13:H13)<2,"",ROUND((G13+(3-H13))/2,1)) | K13: =IF(J13="","Не заполнено",IF(J13<1.5,"Критично",IF(J13<2.3,"Разрыв","ОК")))

Sheet 03_Ритм_доверие
A1: Ритм синхронизации и доверие
A3: Слой | B3: Проверочный вопрос | C3: Оценка, 0-3 | D3: Владелец | E3: Источник | F3: Риск, 0-3 | G3: Комментарий | H3: Статус
A4: Интерфейс | B4: Роли понимают, что должны передавать друг другу. | H4: =IF(C4="","Не заполнено",IF(C4<1.5,"Критично",IF(C4<2.3,"Разрыв","ОК")))
A5: KPI / показатели | B5: Локальные KPI не ломают общий результат. | H5: =IF(C5="","Не заполнено",IF(C5<1.5,"Критично",IF(C5<2.3,"Разрыв","ОК")))
A6: Данные | B6: У ролей есть общая версия фактов. | H6: =IF(C6="","Не заполнено",IF(C6<1.5,"Критично",IF(C6<2.3,"Разрыв","ОК")))
A7: Решения | B7: Конфликт закрывается решением, а не зависает. | H7: =IF(C7="","Не заполнено",IF(C7<1.5,"Критично",IF(C7<2.3,"Разрыв","ОК")))
A8: Обязательства | B8: Стороны фиксируют срок, владельца и следующий шаг. | H8: =IF(C8="","Не заполнено",IF(C8<1.5,"Критично",IF(C8<2.3,"Разрыв","ОК")))
A9: Доверие | B9: Роли выполняют договоренности и не возвращают спор заново. | H9: =IF(C9="","Не заполнено",IF(C9<1.5,"Критично",IF(C9<2.3,"Разрыв","ОК")))
A10: Ритм | B10: Есть регулярная точка синхронизации и review / разбор. | H10: =IF(C10="","Не заполнено",IF(C10<1.5,"Критично",IF(C10<2.3,"Разрыв","ОК")))

Sheet 04_Расчет
A1: Расчёт синхронизации
A3: Показатель | B3: Значение | C3: Норма | D3: Источник | E3: Комментарий | G3: Как читать расчет
A4: Заполненность интерфейсов | B4: =IFERROR(COUNT('02_Интерфейсы'!J4:J13)/10,0) | C4: 80%+ | D4: 02_Интерфейсы | G4: Synchronization Score показывает, насколько C-level-связки способны удерживать общий результат без ручного сглаживания конфликтов.
A5: Средний балл интерфейсов | B5: =IFERROR(AVERAGE('02_Интерфейсы'!J4:J13),"") | C5: 0-3 | D5: 02_Интерфейсы | G5: Критичные зоны передаются в Блок 7, если связка ломается под нагрузкой.
A6: Средний балл ритма и доверия | B6: =IFERROR(AVERAGE('03_Ритм_доверие'!C4:C10),"") | C6: 0-3 | D6: 03_Ритм_доверие
A7: Критичных интерфейсов | B7: =COUNTIF('02_Интерфейсы'!K4:K13,"Критично") | C7: 0 | D7: 02_Интерфейсы
A8: Критичных слоёв ритма/доверия | B8: =COUNTIF('03_Ритм_доверие'!H4:H10,"Критично") | C8: 0 | D8: 03_Ритм_доверие
A9: Synchronization Score | B9: =IF(COUNTA(B5:B6)<2,"",ROUND(AVERAGE(B5:B6)/3*100-IF(B7+B8>0,10,0),0)) | C9: 75+ | D9: Сводный показатель
A10: Статус | B10: =IF(B9="","",IF(B9>=75,"GO / запускать",IF(B9>=50,"HOLD / пауза","NO-GO / остановить"))) | C10: GO / HOLD / NO-GO | D10: Порог Score
A11: Главный риск | B11: =IF(B9="","",IF(B7+B8>0,"Есть критичные разрывы синхронизации",IF(B9<50,"C-level-связки не удерживают общий результат",IF(B9<75,"Есть значимые разрывы KPI, доверия или ритма","Разрывы локальны")))) | C11: Автовывод | D11: Score + критичные зоны
A12: Рекомендуемый следующий блок | B12: ='05_Отчет'!B9 | C12: Ручной выбор | D12: 05_Отчет
A13: Дата обновления | B13: ='01_Ввод'!B5 | C13: Дата | D13: 01_Ввод

Sheet 05_Отчет
A1: Отчёт Блока 6
A3: Поле | B3: Вывод | F3: Формула вывода
A4: Клиент | B4: ='01_Ввод'!B4 | F4: Связка ролей → конфликт KPI / данных → владелец стыка → общий ритм → доверие → следующий блок CLM.
A5: Synchronization Score | B5: ='04_Расчет'!B9
A6: Статус | B6: ='04_Расчет'!B10
A7: Главный риск | B7: ='04_Расчет'!B11
A8: Рекомендуемый следующий блок
A9: Комментарий консультанта
A10: Первое действие 30 дней
A12: Решение для 4 сторон
A13: Сторона | B13: Что показать | C13: Что не включать | D13: Решение
A14: CEO / генеральный директор | B14: Какие связки ролей, KPI и доверия требуют вмешательства | C14: Личные претензии между руководителями
A15: C-level-команда / первый управленческий круг | B15: Правила интерфейса, общий KPI, ритм и обязательства | C15: Обвинительный список конфликтов
A16: Владелец компании | B16: Риск потери результата из-за несшитых функций | C16: Операционные детали без решения
A17: Board / совет директоров | B17: Системные риски синхронизации и следующий блок CLM | C17: Детали внутренних споров
A19: План 30 / 60 / 90
A20: Горизонт | B20: Цель | C20: Действие | D20: Метрика
A21: 30 дней | B21: Закрыть критичные интерфейсы ролей
A22: 60 дней | B22: Сшить KPI, данные, ритм и обязательства
A23: 90 дней | B23: Проверить доверие и устойчивость синхронизации

Sheet 90_Справочник
A1: Типовая связка ролей | B1: Зона синхронизации | D1: Оценка | E1: Риск | F1: Статус | H1: Следующий блок | I1: Когда нужен
A2: CEO / CFO | B2: Стратегия, деньги, инвестиции, ограничения | D2: 0 | E2: 0 | F2: ОК | H2: Блок 7 | I2: Проверить устойчивость C-level-ядра.
A3: CEO / COO | B3: Приоритеты, исполнение, скорость изменений | D3: 1 | E3: 1 | F3: Разрыв | H3: Блок 8 | I3: Перевести лидерство от ручного контроля к мандатам.
A4: CFO / COO | B4: Бюджет, ресурсы, производительность, экономия | D4: 2 | E4: 2 | F4: Критично | H4: Блок 9 | I4: Встроить AI / ИИ в мандаты, данные и ответственность.
A5: CSO Sales / CMO | B5: Спрос, лиды, воронка продаж, качество клиентов | D5: 3 | E5: 3 | H5: Блок 10 | I5: Передать показатели в панель управляемости.
A6: CSO Sales / CPO Product | B6: Обещания рынку, продуктовая ценность, roadmap / дорожная карта | H6: Блок 11 | I6: Собрать дорожную карту перенастройки.
A7: CPO Product / CTO | B7: Продуктовые решения, сроки разработки, технический долг
A8: COO / CHRO | B8: Производительность, оргизменения, люди, нагрузка
A9: CIO / CAO Analytics | B9: Системы, данные, единая версия фактов
A10: CRO Risk / CCO | B10: Риск, допустимость, комплаенс, контроль
A11: CAIO / CIO | B11: AI / ИИ-сценарии, данные, безопасность, интеграция
