Workbook

Sheet 00_Панель
A1: CLM Блок 5. Панель Decision OS
A3: Показатель | B3: Значение | C3: Норма | D3: Комментарий
A4: Клиент | B4: ='01_Ввод'!B4
A5: Количество решений | B5: ='04_Расчет'!B4 | C5: 1+
A6: Готовность Decision Loop | B6: ='04_Расчет'!B6 | C6: 80%+
A7: Возвратов к CEO | B7: ='04_Расчет'!B7 | C7: 0
A8: Decision OS Score | B8: ='04_Расчет'!B9 | C8: 75+
A9: Статус | B9: ='04_Расчет'!B10 | C9: GO / HOLD / NO-GO
A11: Контроль заполнения | F11: Что проверяет Блок 5
A12: Слой | B12: Заполненность / число | C12: Норма | D12: Комментарий | F12: Блок 5 проверяет путь решения: вход, фильтр, владелец, данные, критерии, обязательство, review / разбор.
A13: Реестр решений | B13: ='04_Расчет'!B5 | C13: 80%+ | F13: В книгу не заносятся все операционные вопросы. Только решения C-level-уровня.
A14: Decision Loop | B14: ='04_Расчет'!B6 | C14: 80%+ | F14: AI / ИИ может помогать готовить варианты, но не принимает решение вместо владельца мандата.
A15: Средний риск | B15: ='04_Расчет'!B8 | C15: 0-1
A17: Как пользоваться
A18: 1. Заполните 01_Ввод: разрывы из Блоков 3-4, владелец Decision OS, ритм review / разбора.
A19: 2. На 02_Реестр_решений внесите только C-level-решения, не все операционные вопросы.
A20: 3. На 03_Decision_Loop проверьте семь слоёв пути решения.
A21: 4. 04_Расчет не заполняется вручную.
A22: 5. На 05_Отчет выберите следующий блок и первое действие 30 дней.

Sheet 01_Ввод
A1: CLM Блок 5. Ввод Decision OS / операционной системы решений
A3: Поле | B3: Значение
A4: Клиент
A5: Дата запуска
A6: Главный разрыв из Блока 3
A7: Риск роли из Блока 4
A8: Основной контур решений
A9: Владелец Decision OS
A10: Ритм review / разбора
A11: AI / ИИ используется?
A12: Комментарий
A14: Правило заполнения
A15: 1 | B15: Не заносите все операционные вопросы. Только решения, которые влияют на C-level-ядро.
A16: 2 | B16: Каждое решение должно иметь владельца, данные, критерии, обязательство и review / разбор.
A17: 3 | B17: Если решение постоянно возвращается к CEO, фиксируйте это как управленческий риск.
A18: 4 | B18: AI / ИИ может помогать, но не становится владельцем решения.

Sheet 02_Реестр_решений
A1: Реестр C-level-решений
A3: ID | B3: Решение / вопрос | C3: Тип | D3: Владелец | E3: Почему C-level | F3: Data Pack / пакет данных | G3: Критерии | H3: Статус | I3: Возврат к CEO? | J3: Риск, 0-3 | K3: Срок | L3: Комментарий | M3: Готовность
A4: D-01 | M4: =IF(B4="","",COUNTA(C4:K4)/9)
A5: D-02 | M5: =IF(B5="","",COUNTA(C5:K5)/9)
A6: D-03 | M6: =IF(B6="","",COUNTA(C6:K6)/9)
A7: D-04 | M7: =IF(B7="","",COUNTA(C7:K7)/9)
A8: D-05 | M8: =IF(B8="","",COUNTA(C8:K8)/9)
A9: D-06 | M9: =IF(B9="","",COUNTA(C9:K9)/9)
A10: D-07 | M10: =IF(B10="","",COUNTA(C10:K10)/9)
A11: D-08 | M11: =IF(B11="","",COUNTA(C11:K11)/9)
A12: D-09 | M12: =IF(B12="","",COUNTA(C12:K12)/9)
A13: D-10 | M13: =IF(B13="","",COUNTA(C13:K13)/9)
A14: D-11 | M14: =IF(B14="","",COUNTA(C14:K14)/9)
A15: D-12 | M15: =IF(B15="","",COUNTA(C15:K15)/9)

Sheet 03_Decision_Loop
A1: Decision Loop / цикл решений
A3: Слой | B3: Проверочный вопрос | C3: Ответ | D3: Владелец | E3: Источник | F3: Риск, 0-3 | G3: Комментарий | H3: Статус
A4: Вход | B4: Вопрос или сигнал сформулирован как управленческое решение. | H4: =IF(C4="","Не заполнено",IF(C4="Да","ОК",IF(C4="Нет","Разрыв","Не ясно")))
A5: Фильтр | B5: Понятно, почему вопрос должен попасть на уровень C-level. | H5: =IF(C5="","Не заполнено",IF(C5="Да","ОК",IF(C5="Нет","Разрыв","Не ясно")))
A6: Владелец | B6: Назван владелец решения с мандатом. | H6: =IF(C6="","Не заполнено",IF(C6="Да","ОК",IF(C6="Нет","Разрыв","Не ясно")))
A7: Данные | B7: Есть Data Pack / пакет данных и единая версия фактов. | H7: =IF(C7="","Не заполнено",IF(C7="Да","ОК",IF(C7="Нет","Разрыв","Не ясно")))
A8: Критерии | B8: Понятно, по каким критериям выбирается вариант. | H8: =IF(C8="","Не заполнено",IF(C8="Да","ОК",IF(C8="Нет","Разрыв","Не ясно")))
A9: Решение | B9: Зафиксированы выбор, обязательства, срок и ответственные. | H9: =IF(C9="","Не заполнено",IF(C9="Да","ОК",IF(C9="Нет","Разрыв","Не ясно")))
A10: Review / разбор | B10: Проверено исполнение, эффект, ошибка и урок. | H10: =IF(C10="","Не заполнено",IF(C10="Да","ОК",IF(C10="Нет","Разрыв","Не ясно")))

Sheet 04_Расчет
A1: Расчёт Decision OS
A3: Показатель | B3: Значение | C3: Норма | D3: Источник | E3: Комментарий | G3: Как читать расчет
A4: Количество решений | B4: =COUNTA('02_Реестр_решений'!B4:B15) | C4: 1+ | D4: 02_Реестр_решений | G4: Decision OS Score показывает не качество всех решений компании, а зрелость C-level-контура решений.
A5: Заполненность реестра | B5: =IFERROR(AVERAGE('02_Реестр_решений'!M4:M15),0) | C5: 80%+ | D5: 02_Реестр_решений | G5: Главный риск появляется автоматически: возврат к CEO, слабый цикл решения или локальные разрывы.
A6: Готовность Decision Loop | B6: =IFERROR(COUNTIF('03_Decision_Loop'!C4:C10,"Да")/7,0) | C6: 80%+ | D6: 03_Decision_Loop
A7: Возвратов к CEO | B7: =COUNTIF('02_Реестр_решений'!I4:I15,"Да") | C7: 0 | D7: 02_Реестр_решений
A8: Средний риск решений | B8: =IFERROR(AVERAGE('02_Реестр_решений'!J4:J15),"") | C8: 0-3 | D8: 02_Реестр_решений
A9: Decision OS Score | B9: =IF(B4=0,"",ROUND(AVERAGE(B5:B6)*100-IF(B7>0,10,0)-IF(B8>2,10,0),0)) | C9: 75+ | D9: Сводный показатель
A10: Статус | B10: =IF(B9="","",IF(B9>=75,"GO / запускать",IF(B9>=50,"HOLD / пауза","NO-GO / остановить"))) | C10: GO / HOLD / NO-GO | D10: Порог Score
A11: Главный риск | B11: =IF(B9="","",IF(B7>0,"Решения возвращаются к CEO",IF(B9<50,"Decision OS не удерживает путь решения",IF(B9<75,"Есть разрывы в данных, владельце или review / разборе","Разрывы локальны")))) | C11: Автовывод | D11: Score + возврат к CEO
A12: Рекомендуемый следующий блок | B12: ='05_Отчет'!B9 | C12: Ручной выбор | D12: 05_Отчет
A13: Дата обновления | B13: ='01_Ввод'!B5 | C13: Дата | D13: 01_Ввод

Sheet 05_Отчет
A1: Отчёт Блока 5
A3: Поле | B3: Вывод | F3: Формула вывода
A4: Клиент | B4: ='01_Ввод'!B4 | F4: Сигнал → владелец решения → данные → критерии → обязательство → review / разбор → следующий блок CLM.
A5: Decision OS Score | B5: ='04_Расчет'!B9
A6: Статус | B6: ='04_Расчет'!B10
A7: Главный риск | B7: ='04_Расчет'!B11
A8: Рекомендуемый следующий блок
A9: Комментарий консультанта
A10: Первое действие 30 дней
A12: Решение для 4 сторон
A13: Сторона | B13: Что показать | C13: Что не включать | D13: Решение
A14: CEO / генеральный директор | B14: Где решения возвращаются наверх и какой путь нужно закрепить | C14: Список всех операционных вопросов
A15: C-level-команда / первый управленческий круг | B15: Единый путь решения, владельцы, данные, критерии и review / разбор | C15: Персональные обвинения
A16: Владелец компании | B16: Риск потери управляемости из-за слабых решений | C16: Технические детали таблиц
A17: Board / совет директоров | B17: Статус Decision OS и критические управленческие риски | C17: Операционные мелочи
A19: План 30 / 60 / 90
A20: Горизонт | B20: Цель | C20: Действие | D20: Метрика
A21: 30 дней | B21: Закрепить вход, владельца и критерии решений
A22: 60 дней | B22: Встроить Decision Loop и review / разбор
A23: 90 дней | B23: Проверить исполнение, память решений и снижение возврата к CEO

Sheet 90_Справочник
A1: Тип решения | B1: Смысл | D1: Статус | E1: Оценка | F1: Да / нет | H1: Слой Decision Loop | I1: Смысл
A2: Стратегическое | B2: Меняет направление, модель бизнеса, крупный ресурс или риск. | D2: В работе | E2: 0 | F2: Да | H2: Вход | I2: Вопрос или сигнал сформулирован как управленческое решение.
A3: Финансовое | B3: Влияет на деньги, cash flow / денежный поток, инвестиции или прибыль. | D3: Решено | E3: 1 | F3: Нет | H3: Фильтр | I3: Понятно, почему вопрос должен попасть на уровень C-level.
A4: Клиентское | B4: Влияет на клиента, продукт, рынок или выручку. | D4: Остановлено | E4: 2 | F4: Не ясно | H4: Владелец | I4: Назван владелец решения с мандатом.
A5: Операционное | B5: Влияет на исполнение, процессы, сроки или качество. | E5: 3 | H5: Данные | I5: Есть Data Pack / пакет данных и единая версия фактов.
A6: Рисковое | B6: Влияет на безопасность, устойчивость, комплаенс или репутацию. | H6: Критерии | I6: Понятно, по каким критериям выбирается вариант.
A7: AI / ИИ | B7: Связано с AI / ИИ-сценарием, данными, автоматизацией или выводом модели. | H7: Решение | I7: Зафиксированы выбор, обязательства, срок и ответственные.
H8: Review / разбор | I8: Проверено исполнение, эффект, ошибка и урок.
